mentor/__init__.py
mentor/admin.py
mentor/apps.py
mentor/forms.py
mentor/models.py
mentor/urls.py
mentor/views.py
mentor/static/mentor/css/style.css
mentor/static/mentor/img/about.jpg
mentor/static/mentor/img/apple-touch-icon.png
mentor/static/mentor/img/course-1.jpg
mentor/static/mentor/img/course-2.jpg
mentor/static/mentor/img/course-3.jpg
mentor/static/mentor/img/course-details-tab-1.png
mentor/static/mentor/img/course-details-tab-2.png
mentor/static/mentor/img/course-details-tab-3.png
mentor/static/mentor/img/course-details-tab-4.png
mentor/static/mentor/img/course-details-tab-5.png
mentor/static/mentor/img/course-details.jpg
mentor/static/mentor/img/events-1.jpg
mentor/static/mentor/img/events-2.jpg
mentor/static/mentor/img/favicon.png
mentor/static/mentor/img/hero-bg.jpg
mentor/static/mentor/img/testimonials/testimonials-1.jpg
mentor/static/mentor/img/testimonials/testimonials-2.jpg
mentor/static/mentor/img/testimonials/testimonials-3.jpg
mentor/static/mentor/img/testimonials/testimonials-4.jpg
mentor/static/mentor/img/testimonials/testimonials-5.jpg
mentor/static/mentor/img/trainers/trainer-1.jpg
mentor/static/mentor/img/trainers/trainer-2.jpg
mentor/static/mentor/img/trainers/trainer-3.jpg
mentor/static/mentor/js/main.js
mentor/static/mentor/scss/_footer.scss
mentor/static/mentor/scss/_general.scss
mentor/static/mentor/scss/_header.scss
mentor/static/mentor/scss/_hero.scss
mentor/static/mentor/scss/_nav.scss
mentor/static/mentor/scss/_sections.scss
mentor/static/mentor/scss/_variables.scss
mentor/static/mentor/scss/style.scss
mentor/static/mentor/vendor/animate.css/animate.compat.css
mentor/static/mentor/vendor/animate.css/animate.css
mentor/static/mentor/vendor/animate.css/animate.min.css
mentor/static/mentor/vendor/aos/aos.css
mentor/static/mentor/vendor/aos/aos.js
mentor/static/mentor/vendor/bootstrap/css/bootstrap-grid.css
mentor/static/mentor/vendor/bootstrap/css/bootstrap-grid.css.map
mentor/static/mentor/vendor/bootstrap/css/bootstrap-grid.min.css
django_mentor_ds-0.3.0.dist-info/LICENSE
django_mentor_ds-0.3.0.dist-info/METADATA
django_mentor_ds-0.3.0.dist-info/WHEEL
django_mentor_ds-0.3.0.dist-info/top_level.txt
django_mentor_ds-0.3.0.dist-info/RECORD
